{
  "id": "cairo_opera_house",
  "name": {
    "en": "Cairo Opera House",
    "ar": "دار الأوبرا المصرية"
  },
  "also_known_as": {
    "en": ["National Cultural Center", "New Opera House"],
    "ar": ["المركز الثقافي القومي", "دار الأوبرا الجديدة"]
  },
  "type": "cultural_center",
  "description": {
    "en": "The Cairo Opera House is Egypt's premier performing arts venue and cultural center. Built in 1988 as a replacement for the original Royal Opera House, it serves as the main venue for Cairo's finest musical groups and hosts international performing arts events.",
    "ar": "دار الأوبرا المصرية هي أهم مكان للفنون الأدائية والمركز الثقافي في مصر. بنيت عام 1988 كبديل لدار الأوبرا الملكية الأصلية، وتعمل كمكان رئيسي للفرق الموسيقية المصرية وتستضيف فعاليات الفنون الأدائية الدولية."
  },
  "location": {
    "address": {
      "en": "Gezira Island, Zamalek, Cairo",
      "ar": "جزيرة الجزيرة، الزمالك، القاهرة"
    },
    "coordinates": {
      "latitude": 30.0419,
      "longitude": 31.2244
    },
    "nearby_landmarks": ["Cairo Tower", "Gezira Club", "Nile River"]
  },
  "history": {
    "original_opera_house": {
      "built": 1869,
      "destroyed": 1971,
      "historical_significance": {
        "en": "Built to celebrate the opening of the Suez Canal and hosted the first performance of Verdi's Aida",
        "ar": "بنيت للاحتفال بافتتاح قناة السويس واستضافت أول عرض لأوبرا عايدة لفيردي"
      }
    },
    "current_building": {
      "built": 1988,
      "architect": "Japanese Architecture Team",
      "funded_by": "Japanese Government",
      "style": "Modern Islamic Architecture"
    },
    "significant_events": [
      {
        "year": 1988,
        "event": {
          "en": "Opening of the new Opera House",
          "ar": "افتتاح دار الأوبرا الجديدة"
        }
      },
      {
        "year": 1989,
        "event": {
          "en": "First performance of the Cairo Symphony Orchestra in the new venue",
          "ar": "أول عرض للأوركسترا السيمفونية القاهرية في المكان الجديد"
        }
      }
    ]
  },
  "facilities": {
    "main_hall": {
      "name": {
        "en": "Main Hall",
        "ar": "القاعة الرئيسية"
      },
      "capacity": 1200,
      "features": [
        "Orchestra pit",
        "State-of-the-art acoustics",
        "Modern lighting system"
      ]
    },
    "small_hall": {
      "name": {
        "en": "Small Hall",
        "ar": "القاعة الصغيرة"
      },
      "capacity": 500,
      "features": [
        "Intimate setting",
        "Versatile stage",
        "Perfect for chamber music"
      ]
    },
    "open_air_theater": {
      "name": {
        "en": "Open Air Theater",
        "ar": "المسرح المكشوف"
      },
      "capacity": 600,
      "features": ["Outdoor performances", "Natural acoustics", "Nile view"]
    },
    "additional_facilities": [
      {
        "name": {
          "en": "Art Gallery",
          "ar": "معرض الفنون"
        },
        "description": {
          "en": "Rotating exhibitions of Egyptian and international art",
          "ar": "معارض متغيرة للفن المصري والعالمي"
        }
      },
      {
        "name": {
          "en": "Music Library",
          "ar": "مكتبة الموسيقى"
        },
        "description": {
          "en": "Extensive collection of musical scores and recordings",
          "ar": "مجموعة واسعة من النوتات الموسيقية والتسجيلات"
        }
      },
      {
        "name": {
          "en": "Restaurant",
          "ar": "المطعم"
        },
        "description": {
          "en": "Fine dining with Nile view",
          "ar": "مطعم راقي مع إطلالة على النيل"
        }
      }
    ]
  },
  "performances": {
    "resident_companies": [
      {
        "name": {
          "en": "Cairo Opera Orchestra",
          "ar": "أوركسترا أوبرا القاهرة"
        }
      },
      {
        "name": {
          "en": "Cairo Opera Ballet Company",
          "ar": "فرقة باليه أوبرا القاهرة"
        }
      },
      {
        "name": {
          "en": "Cairo Opera Choir",
          "ar": "كورال أوبرا القاهرة"
        }
      }
    ],
    "regular_events": [
      {
        "name": {
          "en": "Arabic Music Festival",
          "ar": "مهرجان الموسيقى العربية"
        },
        "timing": "November annually"
      },
      {
        "name": {
          "en": "Summer Festival",
          "ar": "مهرجان الصيف"
        },
        "timing": "July-August"
      }
    ],
    "types": [
      "Opera",
      "Symphony concerts",
      "Ballet",
      "Arabic music",
      "Contemporary dance",
      "Theater productions"
    ]
  },
  "practical_information": {
    "opening_hours": {
      "box_office": "10:00 AM - 8:00 PM",
      "building": "Two hours before performances",
      "galleries": "10:00 AM - 2:00 PM"
    },
    "tickets": {
      "booking_methods": ["Online", "Box office", "Phone reservation"],
      "price_range": {
        "opera": "100-500 EGP",
        "concerts": "50-300 EGP",
        "special_events": "200-1000 EGP"
      }
    },
    "dress_code": {
      "en": "Smart casual to formal. No shorts or flip-flops allowed.",
      "ar": "ملابس أنيقة إلى رسمية. غير مسموح بالشورت أو الصندل."
    },
    "facilities": ["Cloakroom", "Cafeteria", "Parking", "Gift shop", "ATM"]
  },
  "visitor_tips": {
    "best_time_to_visit": {
      "en": "Check schedule for preferred performances. Book tickets at least one week in advance for popular shows.",
      "ar": "تحقق من الجدول للعروض المفضلة. احجز التذاكر قبل أسبوع على الأقل للعروض الشعبية."
    },
    "photography": {
      "en": "Not allowed during performances. Permitted in public areas and galleries.",
      "ar": "غير مسموح خلال العروض. مسموح في المناطق العامة والمعارض."
    },
    "what_to_bring": [
      "Tickets",
      "Evening wear for formal performances",
      "Camera (for before/after shows)",
      "Cash for refreshments"
    ]
  },
  "transportation": {
    "metro": {
      "nearest_station": "Opera Station",
      "walking_distance": "5 minutes"
    },
    "bus": {
      "nearby_stops": "Multiple stops on Opera Square",
      "lines": ["Several public bus lines"]
    },
    "parking": {
      "availability": "Available on-site",
      "capacity": "200 cars",
      "cost": "20 EGP per event"
    }
  },
  "nearby_attractions": [
    {
      "id": "cairo_tower",
      "name": {
        "en": "Cairo Tower",
        "ar": "برج القاهرة"
      },
      "distance": "0.5 km"
    },
    {
      "id": "egyptian_museum",
      "name": {
        "en": "Egyptian Museum",
        "ar": "المتحف المصري"
      },
      "distance": "1.5 km"
    }
  ],
  "accessibility": {
    "wheelchair_access": "Available throughout the building",
    "elevators": "To all levels",
    "special_seating": "Available in all venues",
    "assistance": "Staff available to help with special needs"
  },
  "contact": {
    "phone": "+20 2 27390114",
    "email": "info@cairoopera.org",
    "website": "www.cairoopera.org",
    "social_media": {
      "facebook": "CairoOperaHouse",
      "instagram": "cairooperahouse"
    }
  },
  "last_updated": "2024-03-20"
}
